dtapy.py
dtapy-0.0.1.dist-info/METADATA
dtapy-0.0.1.dist-info/WHEEL
dtapy-0.0.1.dist-info/top_level.txt
dtapy-0.0.1.dist-info/RECORD
