Metadata-Version: 2.1
Name: dtapy
Version: 0.0.1
Summary: This package greets you nicely and tells you about its favorite observability platform.
Home-page: UNKNOWN
Author: UNKNOWN
Author-email: UNKNOWN
License: UNKNOWN
Platform: UNKNOWN
